swx_advisories/__init__.py
swx_advisories/adapters/__init__.py
swx_advisories/adapters/dataframe.py
swx_advisories/fetchers/__init__.py
swx_advisories/fetchers/base.py
swx_advisories/fetchers/icao.py
swx_advisories/fetchers/noaa.py
swx_advisories/models/__init__.py
swx_advisories/models/advisory.py
swx_advisories/models/enums.py
swx_advisories/models/location.py
swx_advisories/parsers/__init__.py
swx_advisories/parsers/icao/__init__.py
swx_advisories/parsers/icao/event_builder.py
swx_advisories/parsers/icao/location_parser.py
swx_advisories/parsers/icao/text_parser.py
swx_advisories/parsers/noaa/__init__.py
swx_advisories/parsers/noaa/parser.py
swx_advisories-0.2.0.dist-info/METADATA
swx_advisories-0.2.0.dist-info/WHEEL
swx_advisories-0.2.0.dist-info/RECORD
