Metadata-Version: 2.4
Name: swx-advisories
Version: 0.2.0
Summary: Parse and process space weather advisories from ICAO and NOAA/SWPC
Project-URL: Homepage, https://gitlab.com/KNMI-OSS/spaceweather/swx-advisories
Project-URL: Repository, https://gitlab.com/KNMI-OSS/spaceweather/swx-advisories
Author-email: KNMI <eelco.doornbos@knmi.nl>
License-Expression: Apache-2.0
Keywords: ICAO,NOAA,SWPC,advisories,alerts,aviation,space-weather
Classifier: Development Status :: 3 - Alpha
Classifier: Intended Audience :: Science/Research
Classifier: License :: OSI Approved :: Apache Software License
Classifier: Operating System :: OS Independent
Classifier: Programming Language :: Python :: 3
Classifier: Programming Language :: Python :: 3.10
Classifier: Programming Language :: Python :: 3.11
Classifier: Programming Language :: Python :: 3.12
Classifier: Topic :: Scientific/Engineering :: Atmospheric Science
Requires-Python: >=3.10
Requires-Dist: httpx>=0.25
Requires-Dist: pandas>=2.0
Requires-Dist: pydantic>=2.0
Provides-Extra: dev
Requires-Dist: pytest-asyncio>=0.21; extra == 'dev'
Requires-Dist: pytest>=7.0; extra == 'dev'
Requires-Dist: respx>=0.20; extra == 'dev'
Requires-Dist: ruff>=0.1; extra == 'dev'
